drug_list_ner/.DS_Store
drug_list_ner/__init__.py
drug_list_ner/example.py
drug_list_ner/model2/.DS_Store
drug_list_ner/model2/config.json
drug_list_ner/tokenizer2/special_tokens_map.json
drug_list_ner/tokenizer2/tokenizer.json
drug_list_ner/tokenizer2/tokenizer_config.json
drug_list_ner/tokenizer2/vocab.txt
drug_list_ner-0.1.1.dist-info/METADATA
drug_list_ner-0.1.1.dist-info/WHEEL
drug_list_ner-0.1.1.dist-info/licenses/LICENSE
drug_list_ner-0.1.1.dist-info/RECORD
