Metadata-Version: 2.1
Name: drug_list_ner
Version: 0.1.1
Summary: An NER model to identify prescription drugs in a text sample
Author-email: Ronoy Sarkar <ronoysarkar.mail@gmail.com>
License-File: LICENSE
Classifier: License :: OSI Approved :: MIT License
Classifier: Operating System :: OS Independent
Classifier: Programming Language :: Python :: 3
Requires-Python: >=3.7
Requires-Dist: huggingface-hub
Requires-Dist: torch
Requires-Dist: transformers
